{
  "name": "Prisoner",
  "base": "PersistedModel",
  "idInjection": true,
  "options": {
    "validateUpsert": true
  },
  "properties": {
    "FirstName": {
      "type": "string",
      "required": true
    },
    "LastName": {
      "type": "string",
      "required": true
    },
    "Age": {
      "type": "number",
      "required": true
    },
    "Sentence": {
      "type": "number",
      "required": true,
      "default": 0
    }
  },
  "validations": [],
  "relations": {},
  "acls": [],
  "methods": {}
}
